a_pandas_ex_split/LICENSE
a_pandas_ex_split/README.MD
a_pandas_ex_split/__init__.py
a_pandas_ex_split/requirements.txt
a_pandas_ex_split/thirdparty.json
a_pandas_ex_split-0.10.dist-info/LICENSE.rst
a_pandas_ex_split-0.10.dist-info/METADATA
a_pandas_ex_split-0.10.dist-info/WHEEL
a_pandas_ex_split-0.10.dist-info/top_level.txt
a_pandas_ex_split-0.10.dist-info/RECORD
